irene_package/__init__.py
irene_package/calc.py
irene_package-0.0.2.dist-info/METADATA
irene_package-0.0.2.dist-info/WHEEL
irene_package-0.0.2.dist-info/RECORD
